django_ram/__init__.py
django_ram/admin.py
django_ram/apps.py
django_ram/definition.py
django_ram/models.py
django_ram/migrations/0001_initial.py
django_ram/migrations/0002_role_active.py
django_ram/migrations/__init__.py
django_ram/rest_framework/__init__.py
django_ram/rest_framework/permissions.py
django_ram-0.1.2.dist-info/LICENSE
django_ram-0.1.2.dist-info/METADATA
django_ram-0.1.2.dist-info/WHEEL
django_ram-0.1.2.dist-info/top_level.txt
django_ram-0.1.2.dist-info/RECORD
