Metadata-Version: 2.1
Name: django-ram
Version: 0.1.2
Summary: Django Role based Access Management.
Author-email: Emil van der Westhuizen <vdwemil@protonmail.com>
Project-URL: Homepage, https://github.com/vdwemil95/django-ram
Project-URL: Bug Tracker, https://github.com/vdwemil95/django-ram/issues
Classifier: Programming Language :: Python :: 3
Classifier: License :: OSI Approved :: MIT License
Classifier: Operating System :: OS Independent
Requires-Python: >=3.6
License-File: LICENSE
Requires-Dist: django (>=3.0)
Provides-Extra: rest_framework
Requires-Dist: djangorestframework (<=3.14.0,>=3.10.0) ; extra == 'rest_framework'
